betterpassphrase/__init__.py
betterpassphrase/cli.py
betterpassphrase/config.py
betterpassphrase/generator.py
betterpassphrase/mappings.py
betterpassphrase/models.py
betterpassphrase/utils.py
betterpassphrase/parts_of_speech/adjectives.txt
betterpassphrase/parts_of_speech/adverbs.txt
betterpassphrase/parts_of_speech/conjunctions.txt
betterpassphrase/parts_of_speech/determiners.txt
betterpassphrase/parts_of_speech/obj_nouns.txt
betterpassphrase/parts_of_speech/prepositions.txt
betterpassphrase/parts_of_speech/sub_nouns.txt
betterpassphrase/parts_of_speech/verbs.txt
BetterPassphrase-0.1.7.dist-info/LICENSE.txt
BetterPassphrase-0.1.7.dist-info/METADATA
BetterPassphrase-0.1.7.dist-info/WHEEL
BetterPassphrase-0.1.7.dist-info/entry_points.txt
BetterPassphrase-0.1.7.dist-info/top_level.txt
BetterPassphrase-0.1.7.dist-info/RECORD
