Metadata-Version: 2.2
Name: BetterPassphrase
Version: 0.1.7
Summary: A Python library to generate secure, meaningful passphrases.
Home-page: https://github.com/subhayu99/BetterPassphrase
Author: Subhayu Kumar Bala
Author-email: balasubhayu99@gmail.com
License: MIT
Classifier: Programming Language :: Python :: 3
Classifier: License :: OSI Approved :: MIT License
Classifier: Operating System :: OS Independent
Requires-Python: >=3.10
License-File: LICENSE.txt
Dynamic: author
Dynamic: author-email
Dynamic: classifier
Dynamic: description
Dynamic: description-content-type
Dynamic: home-page
Dynamic: license
Dynamic: requires-python
Dynamic: summary
